commandtemplate/__init__.py
commandtemplate/conda.py
commandtemplate-0.0.1.dist-info/METADATA
commandtemplate-0.0.1.dist-info/WHEEL
commandtemplate-0.0.1.dist-info/top_level.txt
commandtemplate-0.0.1.dist-info/RECORD
